multipletau/__init__.py
multipletau/_version.py
multipletau/core.py
multipletau-0.4.1.dist-info/LICENSE
multipletau-0.4.1.dist-info/METADATA
multipletau-0.4.1.dist-info/WHEEL
multipletau-0.4.1.dist-info/top_level.txt
multipletau-0.4.1.dist-info/RECORD
