Metadata-Version: 2.1
Name: multipletau
Version: 0.4.1
Summary: A multiple-tau algorithm for Python/NumPy
Author: André Scholich, Alexandre Detiste, Chris Lamb, Pascal Hebbeker, Paul Müller
Maintainer-email: Paul Müller <dev@craban.de>
License: BSD (3 clause)
Project-URL: source, https://github.com/FCS-analysis/multipletau
Project-URL: tracker, https://github.com/FCS-analysis/multipletau/issues
Project-URL: documentation, https://multipletau.readthedocs.io/en/stable/
Project-URL: changelog, https://multipletau.readthedocs.io/en/stable/#changelog
Keywords: multiple tau,fluorescence correlation spectroscopy
Classifier: Operating System :: OS Independent
Classifier: Programming Language :: Python :: 3
Classifier: Topic :: Scientific/Engineering :: Visualization
Classifier: Intended Audience :: Science/Research
Requires-Python: <4,>=3.6
License-File: LICENSE
Requires-Dist: numpy >=1.5.1
